{"declines":9,"unchanged":8,"data":[{"metadata":{"symbol":"BAJFINANCE","identifier":"BAJFINANCEEQN","purpose":null,"lastPrice":7500,"change":92.75,"pChange":1.25,"previousClose":7407.25,"finalQuantity":7996,"totalTurnover":59970000,"marketCap":2059582042708.31,"yearHigh":7830,"yearLow":6187.8,"iep":7500,"chartTodayPath":"https://nsearchives.nseindia.com/today/preOpen_BAJFINANCEEQN.svg"},"detail":{"preOpenMarket":{"preopen":[{"price":7480,"buyQty":6,"sellQty":0},{"price":7481.3,"buyQty":1,"sellQty":0},{"price":7490,"buyQty":2,"sellQty":0},{"price":7491.05,"buyQty":1,"sellQty":0},{"price":7500,"buyQty":2357,"sellQty":0,"iep":true},{"price":7500.05,"buyQty":0,"sellQty":10},{"price":7501,"buyQty":0,"sellQty":11},{"price":7501.65,"buyQty":0,"sellQty":11},{"price":7502,"buyQty":0,"sellQty":104},{"price":7505.55,"buyQty":0,"sellQty":1}],"ato":{"totalBuyQuantity":0,"totalSellQuantity":0},"IEP":7500,"totalTradedVolume":7996,"finalPrice":7500,"finalQuantity":7996,"lastUpdateTime":"06-Jan-2025 09:07:05","totalSellQuantity":14544,"totalBuyQuantity":17895,"atoBuyQty":0,"atoSellQty":0,"Change":92.75,"perChange":1.25,"prevClose":7407.25}}},{"metadata":{"symbol":"TITAN","identifier":"TITANEQN","purpose":null,"lastPrice":3490,"change":38.35,"pChange":1.11,"previousClose":3451.65,"finalQuantity":5053,"totalTurnover":17634970,"marketCap":1425532663637.1,"yearHigh":3886.95,"yearLow":3055.65,"iep":3490,"chartTodayPath":"https://nsearchives.nseindia.com/today/preOpen_TITANEQN.svg"},"detail":{"preOpenMarket":{"preopen":[{"price":3470,"buyQty":10,"sellQty":0},{"price":3472.55,"buyQty":57,"sellQty":0},{"price":3480,"buyQty":615,"sellQty":0},{"price":3480.05,"buyQty":3000,"sellQty":0},{"price":3485,"buyQty":3,"sellQty":0},{"price":3490,"buyQty":0,"sellQty":525,"iep":true},{"price":3491,"buyQty":0,"sellQty":15},{"price":3491.65,"buyQty":0,"sellQty":2},{"price":3492,"buyQty":0,"sellQty":3},{"price":3492.9,"buyQty":0,"sellQty":20}],"ato":{"totalBuyQuantity":0,"totalSellQuantity":0},"IEP":3490,"totalTradedVolume":5053,"finalPrice":3490,"finalQuantity":5053,"lastUpdateTime":"06-Jan-2025 09:07:06","totalSellQuantity":14047,"totalBuyQuantity":8294,"atoBuyQty":0,"atoSellQty":0,"Change":38.35,"perChange":1.11,"prevClose":3451.65}}},{"metadata":{"symbol":"TATAMOTORS","identifier":"TATAMOTORSEQN","purpose":null,"lastPrice":797.7,"change":7.3,"pChange":0.92,"previousClose":790.4,"finalQuantity":77704,"totalTurnover":61984480,"marketCap":1651742378487.34,"yearHigh":1179,"yearLow":717.7,"iep":797.7,"chartTodayPath":"https://nsearchives.nseindia.com/today/preOpen_TATAMOTORSEQN.svg"},"detail":{"preOpenMarket":{"preopen":[{"price":795.25,"buyQty":40,"sellQty":0},{"price":795.4,"buyQty":200,"sellQty":0},{"price":796,"buyQty":100,"sellQty":0},{"price":797,"buyQty":19,"sellQty":0},{"price":797.25,"buyQty":1,"sellQty":0},{"price":797.7,"buyQty":0,"sellQty":1301,"iep":true},{"price":797.75,"buyQty":0,"sellQty":50},{"price":797.8,"buyQty":0,"sellQty":5097},{"price":797.85,"buyQty":0,"sellQty":5},{"price":797.9,"buyQty":0,"sellQty":510}],"ato":{"totalBuyQuantity":0,"totalSellQuantity":0},"IEP":797.7,"totalTradedVolume":77704,"finalPrice":797.7,"finalQuantity":77704,"lastUpdateTime":"06-Jan-2025 09:07:05","totalSellQuantity":307092,"totalBuyQuantity":123346,"atoBuyQty":0,"atoSellQty":0,"Change":7.3,"perChange":0.92,"prevClose":790.4}}},{"metadata":{"symbol":"TECHM","identifier":"TECHMEQN","purpose":null,"lastPrice":1704.75,"change":15.3,"pChange":0.91,"previousClose":1689.45,"finalQuantity":1009,"totalTurnover":1720092,"marketCap":1071628388495.58,"yearHigh":1807.7,"yearLow":1162.95,"iep":1704.75,"chartTodayPath":"https://nsearchives.nseindia.com/today/preOpen_TECHMEQN.svg"},"detail":{"preOpenMarket":{"preopen":[{"price":1695,"buyQty":12,"sellQty":0},{"price":1695.45,"buyQty":50,"sellQty":0},{"price":1697.85,"buyQty":25,"sellQty":0},{"price":1700,"buyQty":204,"sellQty":0},{"price":1702.05,"buyQty":2,"sellQty":0},{"price":1704.75,"buyQty":0,"sellQty":8,"iep":true},{"price":1704.8,"buyQty":0,"sellQty":200},{"price":1705,"buyQty":0,"sellQty":2},{"price":1705.5,"buyQty":0,"sellQty":10},{"price":1708,"buyQty":0,"sellQty":52}],"ato":{"totalBuyQuantity":0,"totalSellQuantity":0},"IEP":1704.75,"totalTradedVolume":1009,"finalPrice":1704.75,"finalQuantity":1009,"lastUpdateTime":"06-Jan-2025 09:07:11","totalSellQuantity":13621,"totalBuyQuantity":3984,"atoBuyQty":0,"atoSellQty":0,"Change":15.3,"perChange":0.91,"prevClose":1689.45}}},{"metadata":{"symbol":"BRITANNIA","identifier":"BRITANNIAEQN","purpose":null,"lastPrice":4873.5,"change":39.4,"pChange":0.82,"previousClose":4834.1,"finalQuantity":638,"totalTurnover":3109293,"marketCap":569638938872.96,"yearHigh":6469.9,"yearLow":4641,"iep":4873.5,"chartTodayPath":"https://nsearchives.nseindia.com/today/preOpen_BRITANNIAEQN.svg"},"detail":{"preOpenMarket":{"preopen":[{"price":4840,"buyQty":5,"sellQty":0},{"price":4850,"buyQty":4,"sellQty":0},{"price":4854.1,"buyQty":5,"sellQty":0},{"price":4858.25,"buyQty":3,"sellQty":0},{"price":4869.45,"buyQty":10,"sellQty":0},{"price":4873.5,"buyQty":0,"sellQty":36,"iep":true},{"price":4874,"buyQty":0,"sellQty":26},{"price":4874.8,"buyQty":0,"sellQty":150},{"price":4879,"buyQty":0,"sellQty":121},{"price":4879.3,"buyQty":0,"sellQty":3}],"ato":{"totalBuyQuantity":0,"totalSellQuantity":0},"IEP":4873.5,"totalTradedVolume":638,"finalPrice":4873.5,"finalQuantity":638,"lastUpdateTime":"06-Jan-2025 09:07:06","totalSellQuantity":4804,"totalBuyQuantity":2396,"atoBuyQty":0,"atoSellQty":0,"Change":39.4,"perChange":0.82,"prevClose":4834.1}}},{"metadata":{"symbol":"BAJAJFINSV","identifier":"BAJAJFINSVEQN","purpose":null,"lastPrice":1715,"change":13.9,"pChange":0.82,"previousClose":1701.1,"finalQuantity":3141,"totalTurnover":5386815,"marketCap":927440383694.15,"yearHigh":2029.9,"yearLow":1419.05,"iep":1715,"chartTodayPath":"https://nsearchives.nseindia.com/today/preOpen_BAJAJFINSVEQN.svg"},"detail":{"preOpenMarket":{"preopen":[{"price":1708.05,"buyQty":100,"sellQty":0},{"price":1709.6,"buyQty":6,"sellQty":0},{"price":1709.9,"buyQty":1,"sellQty":0},{"price":1710,"buyQty":20,"sellQty":0},{"price":1715,"buyQty":987,"sellQty":0,"iep":true},{"price":1717,"buyQty":0,"sellQty":21},{"price":1718,"buyQty":0,"sellQty":101},{"price":1718.1,"buyQty":0,"sellQty":1800},{"price":1719,"buyQty":0,"sellQty":6},{"price":1719.9,"buyQty":0,"sellQty":6}],"ato":{"totalBuyQuantity":0,"totalSellQuantity":0},"IEP":1715,"totalTradedVolume":3141,"finalPrice":1715,"finalQuantity":3141,"lastUpdateTime":"06-Jan-2025 09:07:06","totalSellQuantity":20040,"totalBuyQuantity":11248,"atoBuyQty":0,"atoSellQty":0,"Change":13.9,"perChange":0.82,"prevClose":1701.1}}},{"metadata":{"symbol":"INDUSINDBK","identifier":"INDUSINDBKEQN","purpose":null,"lastPrice":1004.95,"change":7.05,"pChange":0.71,"previousClose":997.9,"finalQuantity":6906,"totalTurnover":6940184,"marketCap":657004733645.11,"yearHigh":1694.5,"yearLow":926.45,"iep":1004.95,"chartTodayPath":"https://nsearchives.nseindia.com/today/preOpen_INDUSINDBKEQN.svg"},"detail":{"preOpenMarket":{"preopen":[{"price":1000.25,"buyQty":1,"sellQty":0},{"price":1001,"buyQty":1811,"sellQty":0},{"price":1002.3,"buyQty":122,"sellQty":0},{"price":1002.85,"buyQty":117,"sellQty":0},{"price":1004,"buyQty":60,"sellQty":0},{"price":1004.95,"buyQty":0,"sellQty":41,"iep":true},{"price":1005,"buyQty":0,"sellQty":590},{"price":1005.45,"buyQty":0,"sellQty":50},{"price":1005.5,"buyQty":0,"sellQty":50},{"price":1005.9,"buyQty":0,"sellQty":7010}],"ato":{"totalBuyQuantity":0,"totalSellQuantity":0},"IEP":1004.95,"totalTradedVolume":6906,"finalPrice":1004.95,"finalQuantity":6906,"lastUpdateTime":"06-Jan-2025 09:07:05","totalSellQuantity":61729,"totalBuyQuantity":106507,"atoBuyQty":0,"atoSellQty":0,"Change":7.05,"perChange":0.71,"prevClose":997.9}}},{"metadata":{"symbol":"INFY","identifier":"INFYEQN","purpose":null,"lastPrice":1952,"change":13.25,"pChange":0.68,"previousClose":1938.75,"finalQuantity":15284,"totalTurnover":29834368,"marketCap":6975858052508.07,"yearHigh":2006.45,"yearLow":1358.35,"iep":1952,"chartTodayPath":"https://nsearchives.nseindia.com/today/preOpen_INFYEQN.svg"},"detail":{"preOpenMarket":{"preopen":[{"price":1942.05,"buyQty":100,"sellQty":0},{"price":1943,"buyQty":13,"sellQty":0},{"price":1945,"buyQty":114,"sellQty":0},{"price":1948.4,"buyQty":20,"sellQty":0},{"price":1949,"buyQty":130,"sellQty":0},{"price":1952,"buyQty":0,"sellQty":756,"iep":true},{"price":1952.75,"buyQty":0,"sellQty":30},{"price":1952.95,"buyQty":0,"sellQty":1},{"price":1953.3,"buyQty":0,"sellQty":1},{"price":1954,"buyQty":0,"sellQty":30}],"ato":{"totalBuyQuantity":0,"totalSellQuantity":0},"IEP":1952,"totalTradedVolume":15284,"finalPrice":1952,"finalQuantity":15284,"lastUpdateTime":"06-Jan-2025 09:07:05","totalSellQuantity":62059,"totalBuyQuantity":15472,"atoBuyQty":0,"atoSellQty":0,"Change":13.25,"perChange":0.68,"prevClose":1938.75}}},{"metadata":{"symbol":"LT","identifier":"LTEQN","purpose":null,"lastPrice":3684.75,"change":24.85,"pChange":0.68,"previousClose":3659.9,"finalQuantity":2050,"totalTurnover":7553737,"marketCap":4303080537608.65,"yearHigh":3963.5,"yearLow":3175.05,"iep":3684.75,"chartTodayPath":"https://nsearchives.nseindia.com/today/preOpen_LTEQN.svg"},"detail":{"preOpenMarket":{"preopen":[{"price":3670,"buyQty":62,"sellQty":0},{"price":3670.05,"buyQty":100,"sellQty":0},{"price":3675.4,"buyQty":10,"sellQty":0},{"price":3676.05,"buyQty":100,"sellQty":0},{"price":3678.15,"buyQty":9,"sellQty":0},{"price":3684.75,"buyQty":0,"sellQty":32,"iep":true},{"price":3684.8,"buyQty":0,"sellQty":250},{"price":3684.95,"buyQty":0,"sellQty":9},{"price":3685,"buyQty":0,"sellQty":17},{"price":3689,"buyQty":0,"sellQty":194}],"ato":{"totalBuyQuantity":0,"totalSellQuantity":0},"IEP":3684.75,"totalTradedVolume":2050,"finalPrice":3684.75,"finalQuantity":2050,"lastUpdateTime":"06-Jan-2025 09:07:06","totalSellQuantity":22434,"totalBuyQuantity":11335,"atoBuyQty":0,"atoSellQty":0,"Change":24.85,"perChange":0.68,"prevClose":3659.9}}},{"metadata":{"symbol":"HDFCLIFE","identifier":"HDFCLIFEEQN","purpose":null,"lastPrice":627,"change":4,"pChange":0.64,"previousClose":623,"finalQuantity":7451,"totalTurnover":4671777,"marketCap":666102265570.54,"yearHigh":761.2,"yearLow":511.4,"iep":627,"chartTodayPath":"https://nsearchives.nseindia.com/today/preOpen_HDFCLIFEEQN.svg"},"detail":{"preOpenMarket":{"preopen":[{"price":624,"buyQty":952,"sellQty":0},{"price":624.05,"buyQty":9,"sellQty":0},{"price":624.1,"buyQty":5,"sellQty":0},{"price":625,"buyQty":211,"sellQty":0},{"price":625.05,"buyQty":255,"sellQty":0},{"price":627,"buyQty":0,"sellQty":235,"iep":true},{"price":627.4,"buyQty":0,"sellQty":80},{"price":627.8,"buyQty":0,"sellQty":100},{"price":627.85,"buyQty":0,"sellQty":248},{"price":627.9,"buyQty":0,"sellQty":16}],"ato":{"totalBuyQuantity":0,"totalSellQuantity":0},"IEP":627,"totalTradedVolume":7451,"finalPrice":627,"finalQuantity":7451,"lastUpdateTime":"06-Jan-2025 09:07:06","totalSellQuantity":32331,"totalBuyQuantity":22074,"atoBuyQty":0,"atoSellQty":0,"Change":4,"perChange":0.64,"prevClose":623}}},{"metadata":{"symbol":"M&M","identifier":"M&MEQN","purpose":null,"lastPrice":3209.6,"change":19.05,"pChange":0.6,"previousClose":3190.55,"finalQuantity":4529,"totalTurnover":14536278,"marketCap":2811744084338.32,"yearHigh":3237.05,"yearLow":1575,"iep":3209.6,"chartTodayPath":"https://nsearchives.nseindia.com/today/preOpen_M&MEQN.svg"},"detail":{"preOpenMarket":{"preopen":[{"price":3200,"buyQty":250,"sellQty":0},{"price":3203,"buyQty":1,"sellQty":0},{"price":3205,"buyQty":30,"sellQty":0},{"price":3206,"buyQty":10,"sellQty":0},{"price":3206.5,"buyQty":28,"sellQty":0},{"price":3209.6,"buyQty":0,"sellQty":151,"iep":true},{"price":3209.65,"buyQty":0,"sellQty":296},{"price":3209.9,"buyQty":0,"sellQty":25},{"price":3210,"buyQty":0,"sellQty":1},{"price":3211,"buyQty":0,"sellQty":3}],"ato":{"totalBuyQuantity":0,"totalSellQuantity":0},"IEP":3209.6,"totalTradedVolume":4529,"finalPrice":3209.6,"finalQuantity":4529,"lastUpdateTime":"06-Jan-2025 09:07:05","totalSellQuantity":14969,"totalBuyQuantity":8069,"atoBuyQty":0,"atoSellQty":0,"Change":19.05,"perChange":0.6,"prevClose":3190.55}}},{"metadata":{"symbol":"DRREDDY","identifier":"DRREDDYEQN","purpose":null,"lastPrice":1360.4,"change":7.75,"pChange":0.57,"previousClose":1352.65,"finalQuantity":3837,"totalTurnover":5219854,"marketCap":823014037175.08,"yearHigh":1421.49,"yearLow":1104.13,"iep":1360.4,"chartTodayPath":"https://nsearchives.nseindia.com/today/preOpen_DRREDDYEQN.svg"},"detail":{"preOpenMarket":{"preopen":[{"price":1352.7,"buyQty":6,"sellQty":0},{"price":1353,"buyQty":5,"sellQty":0},{"price":1355,"buyQty":24,"sellQty":0},{"price":1360,"buyQty":2,"sellQty":0},{"price":1360.4,"buyQty":12125,"sellQty":0,"iep":true},{"price":1361.3,"buyQty":0,"sellQty":110},{"price":1362,"buyQty":0,"sellQty":1},{"price":1363.5,"buyQty":0,"sellQty":1},{"price":1364,"buyQty":0,"sellQty":2},{"price":1365,"buyQty":0,"sellQty":1042}],"ato":{"totalBuyQuantity":0,"totalSellQuantity":0},"IEP":1360.4,"totalTradedVolume":3837,"finalPrice":1360.4,"finalQuantity":3837,"lastUpdateTime":"06-Jan-2025 09:07:06","totalSellQuantity":31346,"totalBuyQuantity":16496,"atoBuyQty":0,"atoSellQty":0,"Change":7.75,"perChange":0.57,"prevClose":1352.65}}},{"metadata":{"symbol":"NTPC","identifier":"NTPCEQN","purpose":null,"lastPrice":341.7,"change":1.85,"pChange":0.54,"previousClose":339.85,"finalQuantity":27947,"totalTurnover":9549489,"marketCap":1605477748753.01,"yearHigh":448.45,"yearLow":296.55,"iep":341.7,"chartTodayPath":"https://nsearchives.nseindia.com/today/preOpen_NTPCEQN.svg"},"detail":{"preOpenMarket":{"preopen":[{"price":340.65,"buyQty":238,"sellQty":0},{"price":340.8,"buyQty":1,"sellQty":0},{"price":341,"buyQty":3426,"sellQty":0},{"price":341.05,"buyQty":500,"sellQty":0},{"price":341.5,"buyQty":268,"sellQty":0},{"price":341.7,"buyQty":0,"sellQty":4618,"iep":true},{"price":341.8,"buyQty":0,"sellQty":5},{"price":341.85,"buyQty":0,"sellQty":1},{"price":341.9,"buyQty":0,"sellQty":409},{"price":341.95,"buyQty":0,"sellQty":393}],"ato":{"totalBuyQuantity":0,"totalSellQuantity":0},"IEP":341.7,"totalTradedVolume":27947,"finalPrice":341.7,"finalQuantity":27947,"lastUpdateTime":"06-Jan-2025 09:07:06","totalSellQuantity":139095,"totalBuyQuantity":65014,"atoBuyQty":0,"atoSellQty":0,"Change":1.85,"perChange":0.54,"prevClose":339.85}}},{"metadata":{"symbol":"SBIN","identifier":"SBINEQN","purpose":null,"lastPrice":797.4,"change":4,"pChange":0.5,"previousClose":793.4,"finalQuantity":13929,"totalTurnover":11106984,"marketCap":3048945237273.33,"yearHigh":912,"yearLow":600.65,"iep":797.4,"chartTodayPath":"https://nsearchives.nseindia.com/today/preOpen_SBINEQN.svg"},"detail":{"preOpenMarket":{"preopen":[{"price":796,"buyQty":137,"sellQty":0},{"price":796.65,"buyQty":100,"sellQty":0},{"price":797,"buyQty":142,"sellQty":0},{"price":797.35,"buyQty":422,"sellQty":0},{"price":797.4,"buyQty":197,"sellQty":0,"iep":true},{"price":797.55,"buyQty":0,"sellQty":50},{"price":797.6,"buyQty":0,"sellQty":1000},{"price":797.85,"buyQty":0,"sellQty":2},{"price":797.95,"buyQty":0,"sellQty":1000},{"price":798,"buyQty":0,"sellQty":176}],"ato":{"totalBuyQuantity":0,"totalSellQuantity":0},"IEP":797.4,"totalTradedVolume":13929,"finalPrice":797.4,"finalQuantity":13929,"lastUpdateTime":"06-Jan-2025 09:07:05","totalSellQuantity":241000,"totalBuyQuantity":98379,"atoBuyQty":0,"atoSellQty":0,"Change":4,"perChange":0.5,"prevClose":793.4}}},{"metadata":{"symbol":"HINDUNILVR","identifier":"HINDUNILVREQN","purpose":null,"lastPrice":2418,"change":11.75,"pChange":0.49,"previousClose":2406.25,"finalQuantity":4219,"totalTurnover":10201542,"marketCap":2130509808899.01,"yearHigh":3035,"yearLow":2172.05,"iep":2418,"chartTodayPath":"https://nsearchives.nseindia.com/today/preOpen_HINDUNILVREQN.svg"},"detail":{"preOpenMarket":{"preopen":[{"price":2411.1,"buyQty":4,"sellQty":0},{"price":2411.25,"buyQty":25,"sellQty":0},{"price":2415,"buyQty":5,"sellQty":0},{"price":2417.8,"buyQty":62,"sellQty":0},{"price":2418,"buyQty":483,"sellQty":0,"iep":true},{"price":2418.95,"buyQty":0,"sellQty":25},{"price":2419,"buyQty":0,"sellQty":5},{"price":2419.2,"buyQty":0,"sellQty":4},{"price":2419.25,"buyQty":0,"sellQty":4},{"price":2419.45,"buyQty":0,"sellQty":25}],"ato":{"totalBuyQuantity":0,"totalSellQuantity":0},"IEP":2418,"totalTradedVolume":4219,"finalPrice":2418,"finalQuantity":4219,"lastUpdateTime":"06-Jan-2025 09:10:02","totalSellQuantity":20646,"totalBuyQuantity":15947,"atoBuyQty":0,"atoSellQty":0,"Change":11.75,"perChange":0.49,"prevClose":2406.25}}},{"metadata":{"symbol":"NESTLEIND","identifier":"NESTLEINDEQN","purpose":null,"lastPrice":2243.5,"change":10.8,"pChange":0.48,"previousClose":2232.7,"finalQuantity":2046,"totalTurnover":4590201,"marketCap":797969314450.44,"yearHigh":2778,"yearLow":2145.4,"iep":2243.5,"chartTodayPath":"https://nsearchives.nseindia.com/today/preOpen_NESTLEINDEQN.svg"},"detail":{"preOpenMarket":{"preopen":[{"price":2239,"buyQty":3,"sellQty":0},{"price":2240,"buyQty":42,"sellQty":0},{"price":2241,"buyQty":18,"sellQty":0},{"price":2243.45,"buyQty":116,"sellQty":0},{"price":2243.5,"buyQty":71,"sellQty":0,"iep":true},{"price":2244,"buyQty":0,"sellQty":35},{"price":2244.2,"buyQty":0,"sellQty":6},{"price":2244.9,"buyQty":0,"sellQty":300},{"price":2245,"buyQty":0,"sellQty":4},{"price":2246.35,"buyQty":0,"sellQty":1}],"ato":{"totalBuyQuantity":0,"totalSellQuantity":0},"IEP":2243.5,"totalTradedVolume":2046,"finalPrice":2243.5,"finalQuantity":2046,"lastUpdateTime":"06-Jan-2025 09:07:06","totalSellQuantity":9297,"totalBuyQuantity":20364,"atoBuyQty":0,"atoSellQty":0,"Change":10.8,"perChange":0.48,"prevClose":2232.7}}},{"metadata":{"symbol":"BAJAJ-AUTO","identifier":"BAJAJ-AUTOEQN","purpose":null,"lastPrice":9004.95,"change":39.25,"pChange":0.44,"previousClose":8965.7,"finalQuantity":248,"totalTurnover":2233227,"marketCap":993569170419.32,"yearHigh":12774,"yearLow":6604,"iep":9004.95,"chartTodayPath":"https://nsearchives.nseindia.com/today/preOpen_BAJAJ-AUTOEQN.svg"},"detail":{"preOpenMarket":{"preopen":[{"price":8992,"buyQty":10,"sellQty":0},{"price":8997,"buyQty":2,"sellQty":0},{"price":8999.95,"buyQty":15,"sellQty":0},{"price":9000,"buyQty":1,"sellQty":0},{"price":9000.05,"buyQty":5,"sellQty":0},{"price":9004.95,"buyQty":0,"sellQty":22,"iep":true},{"price":9005,"buyQty":0,"sellQty":1},{"price":9009.7,"buyQty":0,"sellQty":10},{"price":9010,"buyQty":0,"sellQty":1},{"price":9015,"buyQty":0,"sellQty":1}],"ato":{"totalBuyQuantity":0,"totalSellQuantity":0},"IEP":9004.95,"totalTradedVolume":248,"finalPrice":9004.95,"finalQuantity":248,"lastUpdateTime":"06-Jan-2025 09:07:09","totalSellQuantity":3758,"totalBuyQuantity":2462,"atoBuyQty":0,"atoSellQty":0,"Change":39.25,"perChange":0.44,"prevClose":8965.7}}},{"metadata":{"symbol":"HEROMOTOCO","identifier":"HEROMOTOCOEQN","purpose":null,"lastPrice":4259,"change":15.9,"pChange":0.37,"previousClose":4243.1,"finalQuantity":663,"totalTurnover":2823717,"marketCap":548929153918.12,"yearHigh":6246.25,"yearLow":3929.85,"iep":4259,"chartTodayPath":"https://nsearchives.nseindia.com/today/preOpen_HEROMOTOCOEQN.svg"},"detail":{"preOpenMarket":{"preopen":[{"price":4252.4,"buyQty":1,"sellQty":0},{"price":4253,"buyQty":1,"sellQty":0},{"price":4255,"buyQty":8,"sellQty":0},{"price":4257.05,"buyQty":100,"sellQty":0},{"price":4257.4,"buyQty":1,"sellQty":0},{"price":4259,"buyQty":0,"sellQty":51,"iep":true},{"price":4260,"buyQty":0,"sellQty":7},{"price":4265,"buyQty":0,"sellQty":1},{"price":4267,"buyQty":0,"sellQty":5},{"price":4267.45,"buyQty":0,"sellQty":250}],"ato":{"totalBuyQuantity":0,"totalSellQuantity":0},"IEP":4259,"totalTradedVolume":663,"finalPrice":4259,"finalQuantity":663,"lastUpdateTime":"06-Jan-2025 09:07:06","totalSellQuantity":7316,"totalBuyQuantity":5178,"atoBuyQty":0,"atoSellQty":0,"Change":15.9,"perChange":0.37,"prevClose":4243.1}}},{"metadata":{"symbol":"GRASIM","identifier":"GRASIMEQN","purpose":null,"lastPrice":2517,"change":7,"pChange":0.28,"previousClose":2510,"finalQuantity":388,"totalTurnover":976596,"marketCap":933317727912.62,"yearHigh":2877.75,"yearLow":2016.55,"iep":2517,"chartTodayPath":"https://nsearchives.nseindia.com/today/preOpen_GRASIMEQN.svg"},"detail":{"preOpenMarket":{"preopen":[{"price":2510.6,"buyQty":2,"sellQty":0},{"price":2511,"buyQty":1,"sellQty":0},{"price":2512,"buyQty":5,"sellQty":0},{"price":2515,"buyQty":30,"sellQty":0},{"price":2517,"buyQty":7,"sellQty":0,"iep":true},{"price":2518.7,"buyQty":0,"sellQty":2},{"price":2518.75,"buyQty":0,"sellQty":2},{"price":2518.9,"buyQty":0,"sellQty":1},{"price":2524,"buyQty":0,"sellQty":21},{"price":2529.9,"buyQty":0,"sellQty":1}],"ato":{"totalBuyQuantity":0,"totalSellQuantity":0},"IEP":2517,"totalTradedVolume":388,"finalPrice":2517,"finalQuantity":388,"lastUpdateTime":"06-Jan-2025 09:07:11","totalSellQuantity":5863,"totalBuyQuantity":2422,"atoBuyQty":0,"atoSellQty":0,"Change":7,"perChange":0.28,"prevClose":2510}}},{"metadata":{"symbol":"AXISBANK","identifier":"AXISBANKEQN","purpose":null,"lastPrice":1087.75,"change":2.85,"pChange":0.26,"previousClose":1084.9,"finalQuantity":5295,"totalTurnover":5759636,"marketCap":3079636206433.41,"yearHigh":1339.65,"yearLow":995.7,"iep":1087.75,"chartTodayPath":"https://nsearchives.nseindia.com/today/preOpen_AXISBANKEQN.svg"},"detail":{"preOpenMarket":{"preopen":[{"price":1085,"buyQty":156,"sellQty":0},{"price":1085.05,"buyQty":3,"sellQty":0},{"price":1085.1,"buyQty":23,"sellQty":0},{"price":1085.6,"buyQty":27,"sellQty":0},{"price":1087.1,"buyQty":500,"sellQty":0},{"price":1087.75,"buyQty":0,"sellQty":1841,"iep":true},{"price":1088.9,"buyQty":0,"sellQty":1},{"price":1088.95,"buyQty":0,"sellQty":1},{"price":1089,"buyQty":0,"sellQty":735},{"price":1089.95,"buyQty":0,"sellQty":4}],"ato":{"totalBuyQuantity":0,"totalSellQuantity":0},"IEP":1087.75,"totalTradedVolume":5295,"finalPrice":1087.75,"finalQuantity":5295,"lastUpdateTime":"06-Jan-2025 09:07:06","totalSellQuantity":34164,"totalBuyQuantity":20332,"atoBuyQty":0,"atoSellQty":0,"Change":2.85,"perChange":0.26,"prevClose":1084.9}}},{"metadata":{"symbol":"HINDALCO","identifier":"HINDALCOEQN","purpose":null,"lastPrice":592.6,"change":1.45,"pChange":0.25,"previousClose":591.15,"finalQuantity":16678,"totalTurnover":9883382,"marketCap":856915942525.16,"yearHigh":772.65,"yearLow":496.35,"iep":592.6,"chartTodayPath":"https://nsearchives.nseindia.com/today/preOpen_HINDALCOEQN.svg"},"detail":{"preOpenMarket":{"preopen":[{"price":592.1,"buyQty":5,"sellQty":0},{"price":592.2,"buyQty":5000,"sellQty":0},{"price":592.4,"buyQty":100,"sellQty":0},{"price":592.5,"buyQty":1,"sellQty":0},{"price":592.6,"buyQty":227,"sellQty":0,"iep":true},{"price":592.65,"buyQty":0,"sellQty":10},{"price":593,"buyQty":0,"sellQty":185},{"price":593.9,"buyQty":0,"sellQty":53},{"price":594,"buyQty":0,"sellQty":3},{"price":594.2,"buyQty":0,"sellQty":500}],"ato":{"totalBuyQuantity":0,"totalSellQuantity":0},"IEP":592.6,"totalTradedVolume":16678,"finalPrice":592.6,"finalQuantity":16678,"lastUpdateTime":"06-Jan-2025 09:07:06","totalSellQuantity":31073,"totalBuyQuantity":71084,"atoBuyQty":0,"atoSellQty":0,"Change":1.45,"perChange":0.25,"prevClose":591.15}}},{"metadata":{"symbol":"HCLTECH","identifier":"HCLTECHEQN","purpose":null,"lastPrice":1951.25,"change":4.6,"pChange":0.24,"previousClose":1946.65,"finalQuantity":3207,"totalTurnover":6257658,"marketCap":2054172212770.49,"yearHigh":1992.1,"yearLow":1235,"iep":1951.25,"chartTodayPath":"https://nsearchives.nseindia.com/today/preOpen_HCLTECHEQN.svg"},"detail":{"preOpenMarket":{"preopen":[{"price":1948,"buyQty":1,"sellQty":0},{"price":1950,"buyQty":407,"sellQty":0},{"price":1950.05,"buyQty":100,"sellQty":0},{"price":1950.4,"buyQty":125,"sellQty":0},{"price":1951,"buyQty":2,"sellQty":0},{"price":1951.25,"buyQty":0,"sellQty":6,"iep":true},{"price":1951.45,"buyQty":0,"sellQty":192},{"price":1952,"buyQty":0,"sellQty":50},{"price":1953.4,"buyQty":0,"sellQty":3},{"price":1953.45,"buyQty":0,"sellQty":3}],"ato":{"totalBuyQuantity":0,"totalSellQuantity":0},"IEP":1951.25,"totalTradedVolume":3207,"finalPrice":1951.25,"finalQuantity":3207,"lastUpdateTime":"06-Jan-2025 09:07:05","totalSellQuantity":25109,"totalBuyQuantity":5972,"atoBuyQty":0,"atoSellQty":0,"Change":4.6,"perChange":0.24,"prevClose":1946.65}}},{"metadata":{"symbol":"ICICIBANK","identifier":"ICICIBANKEQN","purpose":null,"lastPrice":1268.05,"change":3,"pChange":0.24,"previousClose":1265.05,"finalQuantity":22168,"totalTurnover":28110132,"marketCap":8920392315956.48,"yearHigh":1362.35,"yearLow":970.15,"iep":1268.05,"chartTodayPath":"https://nsearchives.nseindia.com/today/preOpen_ICICIBANKEQN.svg"},"detail":{"preOpenMarket":{"preopen":[{"price":1266,"buyQty":5011,"sellQty":0},{"price":1266.1,"buyQty":25,"sellQty":0},{"price":1267,"buyQty":789,"sellQty":0},{"price":1267.25,"buyQty":1,"sellQty":0},{"price":1268,"buyQty":595,"sellQty":0},{"price":1268.05,"buyQty":0,"sellQty":138,"iep":true},{"price":1268.2,"buyQty":0,"sellQty":4},{"price":1268.25,"buyQty":0,"sellQty":4},{"price":1268.5,"buyQty":0,"sellQty":10},{"price":1269.35,"buyQty":0,"sellQty":118}],"ato":{"totalBuyQuantity":0,"totalSellQuantity":0},"IEP":1268.05,"totalTradedVolume":22168,"finalPrice":1268.05,"finalQuantity":22168,"lastUpdateTime":"06-Jan-2025 09:07:06","totalSellQuantity":93713,"totalBuyQuantity":59897,"atoBuyQty":0,"atoSellQty":0,"Change":3,"perChange":0.24,"prevClose":1265.05}}},{"metadata":{"symbol":"RELIANCE","identifier":"RELIANCEEQN","purpose":null,"lastPrice":1253.95,"change":2.8,"pChange":0.22,"previousClose":1251.15,"finalQuantity":62250,"totalTurnover":78058387,"marketCap":8473648482985.48,"yearHigh":1608.8,"yearLow":1201.5,"iep":1253.95,"chartTodayPath":"https://nsearchives.nseindia.com/today/preOpen_RELIANCEEQN.svg"},"detail":{"preOpenMarket":{"preopen":[{"price":1252.15,"buyQty":50,"sellQty":0},{"price":1252.2,"buyQty":5,"sellQty":0},{"price":1252.85,"buyQty":130,"sellQty":0},{"price":1253,"buyQty":2065,"sellQty":0},{"price":1253.2,"buyQty":25,"sellQty":0},{"price":1253.95,"buyQty":0,"sellQty":398,"iep":true},{"price":1254,"buyQty":0,"sellQty":2939},{"price":1254.85,"buyQty":0,"sellQty":1},{"price":1254.9,"buyQty":0,"sellQty":1},{"price":1254.95,"buyQty":0,"sellQty":100}],"ato":{"totalBuyQuantity":0,"totalSellQuantity":0},"IEP":1253.95,"totalTradedVolume":62250,"finalPrice":1253.95,"finalQuantity":62250,"lastUpdateTime":"06-Jan-2025 09:07:05","totalSellQuantity":209069,"totalBuyQuantity":147535,"atoBuyQty":0,"atoSellQty":0,"Change":2.8,"perChange":0.22,"prevClose":1251.15}}},{"metadata":{"symbol":"BEL","identifier":"BELEQN","purpose":null,"lastPrice":292.55,"change":0.6,"pChange":0.21,"previousClose":291.95,"finalQuantity":44685,"totalTurnover":13072596,"marketCap":1042778227979.18,"yearHigh":340.5,"yearLow":171.75,"iep":292.55,"chartTodayPath":"https://nsearchives.nseindia.com/today/preOpen_BELEQN.svg"},"detail":{"preOpenMarket":{"preopen":[{"price":292.05,"buyQty":1050,"sellQty":0},{"price":292.1,"buyQty":150,"sellQty":0},{"price":292.25,"buyQty":50,"sellQty":0},{"price":292.4,"buyQty":371,"sellQty":0},{"price":292.5,"buyQty":880,"sellQty":0},{"price":292.55,"buyQty":0,"sellQty":685,"iep":true},{"price":292.6,"buyQty":0,"sellQty":4714},{"price":292.8,"buyQty":0,"sellQty":963},{"price":292.9,"buyQty":0,"sellQty":280},{"price":292.95,"buyQty":0,"sellQty":300}],"ato":{"totalBuyQuantity":0,"totalSellQuantity":0},"IEP":292.55,"totalTradedVolume":44685,"finalPrice":292.55,"finalQuantity":44685,"lastUpdateTime":"06-Jan-2025 09:07:06","totalSellQuantity":513347,"totalBuyQuantity":155569,"atoBuyQty":0,"atoSellQty":0,"Change":0.6,"perChange":0.21,"prevClose":291.95}}},{"metadata":{"symbol":"WIPRO","identifier":"WIPROEQN","purpose":null,"lastPrice":295,"change":0.55,"pChange":0.19,"previousClose":294.45,"finalQuantity":40712,"totalTurnover":12010040,"marketCap":834918911316.49,"yearHigh":320,"yearLow":208.5,"iep":295,"chartTodayPath":"https://nsearchives.nseindia.com/today/preOpen_WIPROEQN.svg"},"detail":{"preOpenMarket":{"preopen":[{"price":294.45,"buyQty":13970,"sellQty":0},{"price":294.5,"buyQty":12407,"sellQty":0},{"price":294.55,"buyQty":115,"sellQty":0},{"price":294.6,"buyQty":100,"sellQty":0},{"price":294.65,"buyQty":2,"sellQty":0},{"price":295,"buyQty":0,"sellQty":1011,"iep":true},{"price":295.1,"buyQty":0,"sellQty":600},{"price":295.15,"buyQty":0,"sellQty":100},{"price":295.2,"buyQty":0,"sellQty":122},{"price":295.4,"buyQty":0,"sellQty":100}],"ato":{"totalBuyQuantity":0,"totalSellQuantity":0},"IEP":295,"totalTradedVolume":40712,"finalPrice":295,"finalQuantity":40712,"lastUpdateTime":"06-Jan-2025 09:07:05","totalSellQuantity":303822,"totalBuyQuantity":87850,"atoBuyQty":0,"atoSellQty":0,"Change":0.55,"perChange":0.19,"prevClose":294.45}}},{"metadata":{"symbol":"SBILIFE","identifier":"SBILIFEEQN","purpose":null,"lastPrice":1450,"change":2.3,"pChange":0.16,"previousClose":1447.7,"finalQuantity":2520,"totalTurnover":3654000,"marketCap":648064033561.45,"yearHigh":1936,"yearLow":1307.7,"iep":1450,"chartTodayPath":"https://nsearchives.nseindia.com/today/preOpen_SBILIFEEQN.svg"},"detail":{"preOpenMarket":{"preopen":[{"price":1446,"buyQty":100,"sellQty":0},{"price":1447,"buyQty":7,"sellQty":0},{"price":1447.7,"buyQty":618,"sellQty":0},{"price":1448,"buyQty":104,"sellQty":0},{"price":1449,"buyQty":18,"sellQty":0},{"price":1450,"buyQty":0,"sellQty":1289,"iep":true},{"price":1450.95,"buyQty":0,"sellQty":50},{"price":1451,"buyQty":0,"sellQty":1},{"price":1452,"buyQty":0,"sellQty":102},{"price":1452.7,"buyQty":0,"sellQty":4}],"ato":{"totalBuyQuantity":0,"totalSellQuantity":0},"IEP":1450,"totalTradedVolume":2520,"finalPrice":1450,"finalQuantity":2520,"lastUpdateTime":"06-Jan-2025 09:07:11","totalSellQuantity":13797,"totalBuyQuantity":6219,"atoBuyQty":0,"atoSellQty":0,"Change":2.3,"perChange":0.16,"prevClose":1447.7}}},{"metadata":{"symbol":"TCS","identifier":"TCSEQN","purpose":null,"lastPrice":4105.5,"change":5.6,"pChange":0.14,"previousClose":4099.9,"finalQuantity":7653,"totalTurnover":31419391,"marketCap":4181580100204.69,"yearHigh":4592.25,"yearLow":3591.5,"iep":4105.5,"chartTodayPath":"https://nsearchives.nseindia.com/today/preOpen_TCSEQN.svg"},"detail":{"preOpenMarket":{"preopen":[{"price":4103,"buyQty":1,"sellQty":0},{"price":4104,"buyQty":550,"sellQty":0},{"price":4105,"buyQty":265,"sellQty":0},{"price":4105.1,"buyQty":50,"sellQty":0},{"price":4105.5,"buyQty":280,"sellQty":0,"iep":true},{"price":4108.9,"buyQty":0,"sellQty":1},{"price":4109,"buyQty":0,"sellQty":1},{"price":4109.25,"buyQty":0,"sellQty":36},{"price":4109.95,"buyQty":0,"sellQty":1},{"price":4110,"buyQty":0,"sellQty":4}],"ato":{"totalBuyQuantity":0,"totalSellQuantity":0},"IEP":4105.5,"totalTradedVolume":7653,"finalPrice":4105.5,"finalQuantity":7653,"lastUpdateTime":"06-Jan-2025 09:07:06","totalSellQuantity":18265,"totalBuyQuantity":14169,"atoBuyQty":0,"atoSellQty":0,"Change":5.6,"perChange":0.14,"prevClose":4099.9}}},{"metadata":{"symbol":"ULTRACEMCO","identifier":"ULTRACEMCOEQN","purpose":null,"lastPrice":11801.95,"change":15.95,"pChange":0.14,"previousClose":11786,"finalQuantity":176,"totalTurnover":2077143,"marketCap":1338907705236.21,"yearHigh":12145.35,"yearLow":9250,"iep":11801.95,"chartTodayPath":"https://nsearchives.nseindia.com/today/preOpen_ULTRACEMCOEQN.svg"},"detail":{"preOpenMarket":{"preopen":[{"price":11786,"buyQty":3,"sellQty":0},{"price":11786.1,"buyQty":3,"sellQty":0},{"price":11789,"buyQty":3,"sellQty":0},{"price":11800,"buyQty":5,"sellQty":0},{"price":11801.95,"buyQty":10,"sellQty":0,"iep":true},{"price":11807,"buyQty":0,"sellQty":1},{"price":11825,"buyQty":0,"sellQty":9},{"price":11828,"buyQty":0,"sellQty":3},{"price":11850,"buyQty":0,"sellQty":42},{"price":11853,"buyQty":0,"sellQty":9}],"ato":{"totalBuyQuantity":0,"totalSellQuantity":0},"IEP":11801.95,"totalTradedVolume":176,"finalPrice":11801.95,"finalQuantity":176,"lastUpdateTime":"06-Jan-2025 09:07:06","totalSellQuantity":1449,"totalBuyQuantity":775,"atoBuyQty":0,"atoSellQty":0,"Change":15.95,"perChange":0.14,"prevClose":11786}}},{"metadata":{"symbol":"COALINDIA","identifier":"COALINDIAEQN","purpose":null,"lastPrice":394.05,"change":0.4,"pChange":0.1,"previousClose":393.65,"finalQuantity":25965,"totalTurnover":10231508,"marketCap":892711738441.7,"yearHigh":543.55,"yearLow":368,"iep":394.05,"chartTodayPath":"https://nsearchives.nseindia.com/today/preOpen_COALINDIAEQN.svg"},"detail":{"preOpenMarket":{"preopen":[{"price":393.7,"buyQty":102,"sellQty":0},{"price":393.8,"buyQty":1,"sellQty":0},{"price":393.9,"buyQty":27,"sellQty":0},{"price":393.95,"buyQty":86,"sellQty":0},{"price":394,"buyQty":1268,"sellQty":0},{"price":394.05,"buyQty":0,"sellQty":5629,"iep":true},{"price":394.1,"buyQty":0,"sellQty":52},{"price":394.4,"buyQty":0,"sellQty":225},{"price":394.95,"buyQty":0,"sellQty":1000},{"price":395,"buyQty":0,"sellQty":220}],"ato":{"totalBuyQuantity":0,"totalSellQuantity":0},"IEP":394.05,"totalTradedVolume":25965,"finalPrice":394.05,"finalQuantity":25965,"lastUpdateTime":"06-Jan-2025 09:07:06","totalSellQuantity":152487,"totalBuyQuantity":82988,"atoBuyQty":0,"atoSellQty":0,"Change":0.4,"perChange":0.1,"prevClose":393.65}}},{"metadata":{"symbol":"ONGC","identifier":"ONGCEQN","purpose":null,"lastPrice":259.11,"change":0.22,"pChange":0.08,"previousClose":258.89,"finalQuantity":55278,"totalTurnover":14323082,"marketCap":1001947329252.94,"yearHigh":345,"yearLow":204.5,"iep":259.11,"chartTodayPath":"https://nsearchives.nseindia.com/today/preOpen_ONGCEQN.svg"},"detail":{"preOpenMarket":{"preopen":[{"price":259,"buyQty":2971,"sellQty":0},{"price":259.05,"buyQty":1250,"sellQty":0},{"price":259.07,"buyQty":9,"sellQty":0},{"price":259.1,"buyQty":1690,"sellQty":0},{"price":259.11,"buyQty":1181,"sellQty":0,"iep":true},{"price":259.2,"buyQty":0,"sellQty":1000},{"price":259.3,"buyQty":0,"sellQty":500},{"price":259.35,"buyQty":0,"sellQty":900},{"price":259.4,"buyQty":0,"sellQty":678},{"price":259.5,"buyQty":0,"sellQty":2135}],"ato":{"totalBuyQuantity":0,"totalSellQuantity":0},"IEP":259.11,"totalTradedVolume":55278,"finalPrice":259.11,"finalQuantity":55278,"lastUpdateTime":"06-Jan-2025 09:07:05","totalSellQuantity":443563,"totalBuyQuantity":193001,"atoBuyQty":0,"atoSellQty":0,"Change":0.22,"perChange":0.08,"prevClose":258.89}}},{"metadata":{"symbol":"SUNPHARMA","identifier":"SUNPHARMAEQN","purpose":null,"lastPrice":1850.5,"change":0.85,"pChange":0.05,"previousClose":1849.65,"finalQuantity":2603,"totalTurnover":4816851,"marketCap":1992919379360.86,"yearHigh":1960.35,"yearLow":1287,"iep":1850.5,"chartTodayPath":"https://nsearchives.nseindia.com/today/preOpen_SUNPHARMAEQN.svg"},"detail":{"preOpenMarket":{"preopen":[{"price":1849.7,"buyQty":52,"sellQty":0},{"price":1849.85,"buyQty":17,"sellQty":0},{"price":1850,"buyQty":569,"sellQty":0},{"price":1850.05,"buyQty":2,"sellQty":0},{"price":1850.5,"buyQty":141,"sellQty":0,"iep":true},{"price":1853,"buyQty":0,"sellQty":1},{"price":1854.15,"buyQty":0,"sellQty":80},{"price":1855,"buyQty":0,"sellQty":12},{"price":1858,"buyQty":0,"sellQty":15},{"price":1858.9,"buyQty":0,"sellQty":292}],"ato":{"totalBuyQuantity":0,"totalSellQuantity":0},"IEP":1850.5,"totalTradedVolume":2603,"finalPrice":1850.5,"finalQuantity":2603,"lastUpdateTime":"06-Jan-2025 09:07:11","totalSellQuantity":11891,"totalBuyQuantity":5225,"atoBuyQty":0,"atoSellQty":0,"Change":0.85,"perChange":0.05,"prevClose":1849.65}}},{"metadata":{"symbol":"ADANIPORTS","identifier":"ADANIPORTSEQN","purpose":null,"lastPrice":1199.55,"change":0,"pChange":0,"previousClose":1199.55,"finalQuantity":6402,"totalTurnover":7679519,"marketCap":881710627324.52,"yearHigh":1621.4,"yearLow":995.65,"iep":1199.55,"chartTodayPath":"https://nsearchives.nseindia.com/today/preOpen_ADANIPORTSEQN.svg"},"detail":{"preOpenMarket":{"preopen":[{"price":1197.8,"buyQty":264,"sellQty":0},{"price":1197.85,"buyQty":2,"sellQty":0},{"price":1198,"buyQty":21,"sellQty":0},{"price":1199,"buyQty":197,"sellQty":0},{"price":1199.5,"buyQty":10,"sellQty":0},{"price":1199.55,"buyQty":0,"sellQty":684,"iep":true},{"price":1200,"buyQty":0,"sellQty":75},{"price":1202,"buyQty":0,"sellQty":137},{"price":1204,"buyQty":0,"sellQty":1},{"price":1204.15,"buyQty":0,"sellQty":15}],"ato":{"totalBuyQuantity":0,"totalSellQuantity":0},"IEP":1199.55,"totalTradedVolume":6402,"finalPrice":1199.55,"finalQuantity":6402,"lastUpdateTime":"06-Jan-2025 09:07:06","totalSellQuantity":46542,"totalBuyQuantity":20776,"atoBuyQty":0,"atoSellQty":0,"Change":0,"perChange":0,"prevClose":1199.55}}},{"metadata":{"symbol":"TRENT","identifier":"TRENTEQN","purpose":null,"lastPrice":7307.7,"change":0,"pChange":0,"previousClose":7307.7,"finalQuantity":717,"totalTurnover":5239620,"marketCap":1615447612452.71,"yearHigh":8345,"yearLow":2955,"iep":7307.7,"chartTodayPath":"https://nsearchives.nseindia.com/today/preOpen_TRENTEQN.svg"},"detail":{"preOpenMarket":{"preopen":[{"price":7305,"buyQty":3,"sellQty":0},{"price":7306.6,"buyQty":5,"sellQty":0},{"price":7306.95,"buyQty":2,"sellQty":0},{"price":7307,"buyQty":6,"sellQty":0},{"price":7307.55,"buyQty":5,"sellQty":0},{"price":7307.7,"buyQty":0,"sellQty":157,"iep":true},{"price":7320,"buyQty":0,"sellQty":12},{"price":7320.5,"buyQty":0,"sellQty":25},{"price":7330,"buyQty":0,"sellQty":1},{"price":7331,"buyQty":0,"sellQty":1}],"ato":{"totalBuyQuantity":0,"totalSellQuantity":0},"IEP":7307.7,"totalTradedVolume":717,"finalPrice":7307.7,"finalQuantity":717,"lastUpdateTime":"06-Jan-2025 09:07:08","totalSellQuantity":7526,"totalBuyQuantity":3330,"atoBuyQty":0,"atoSellQty":0,"Change":0,"perChange":0,"prevClose":7307.7}}},{"metadata":{"symbol":"BPCL","identifier":"BPCLEQN","purpose":null,"lastPrice":296.4,"change":0,"pChange":0,"previousClose":296.4,"finalQuantity":10203,"totalTurnover":3024169,"marketCap":573508057838.26,"yearHigh":376,"yearLow":222.55,"iep":296.4,"chartTodayPath":"https://nsearchives.nseindia.com/today/preOpen_BPCLEQN.svg"},"detail":{"preOpenMarket":{"preopen":[{"price":295.95,"buyQty":7,"sellQty":0},{"price":296,"buyQty":18230,"sellQty":0},{"price":296.1,"buyQty":18,"sellQty":0},{"price":296.15,"buyQty":3,"sellQty":0},{"price":296.25,"buyQty":1,"sellQty":0},{"price":296.4,"buyQty":0,"sellQty":1490,"iep":true},{"price":296.6,"buyQty":0,"sellQty":2},{"price":296.7,"buyQty":0,"sellQty":1100},{"price":296.8,"buyQty":0,"sellQty":201},{"price":296.9,"buyQty":0,"sellQty":432}],"ato":{"totalBuyQuantity":0,"totalSellQuantity":0},"IEP":296.4,"totalTradedVolume":10203,"finalPrice":296.4,"finalQuantity":10203,"lastUpdateTime":"06-Jan-2025 09:07:05","totalSellQuantity":151512,"totalBuyQuantity":65944,"atoBuyQty":0,"atoSellQty":0,"Change":0,"perChange":0,"prevClose":296.4}}},{"metadata":{"symbol":"JSWSTEEL","identifier":"JSWSTEELEQN","purpose":null,"lastPrice":915.05,"change":0,"pChange":0,"previousClose":915.05,"finalQuantity":1457,"totalTurnover":1333227,"marketCap":875026180461.03,"yearHigh":1063,"yearLow":761.75,"iep":915.05,"chartTodayPath":"https://nsearchives.nseindia.com/today/preOpen_JSWSTEELEQN.svg"},"detail":{"preOpenMarket":{"preopen":[{"price":912,"buyQty":35,"sellQty":0},{"price":913,"buyQty":16,"sellQty":0},{"price":913.6,"buyQty":2,"sellQty":0},{"price":915,"buyQty":106,"sellQty":0},{"price":915.05,"buyQty":197,"sellQty":0,"iep":true},{"price":918,"buyQty":0,"sellQty":152},{"price":919.9,"buyQty":0,"sellQty":25},{"price":920,"buyQty":0,"sellQty":42},{"price":920.95,"buyQty":0,"sellQty":50},{"price":921,"buyQty":0,"sellQty":1}],"ato":{"totalBuyQuantity":0,"totalSellQuantity":0},"IEP":915.05,"totalTradedVolume":1457,"finalPrice":915.05,"finalQuantity":1457,"lastUpdateTime":"06-Jan-2025 09:07:09","totalSellQuantity":23312,"totalBuyQuantity":4129,"atoBuyQty":0,"atoSellQty":0,"Change":0,"perChange":0,"prevClose":915.05}}},{"metadata":{"symbol":"TATASTEEL","identifier":"TATASTEELEQN","purpose":null,"lastPrice":138.36,"change":0,"pChange":0,"previousClose":138.36,"finalQuantity":90484,"totalTurnover":12519366,"marketCap":1144743689725,"yearHigh":184.6,"yearLow":128.2,"iep":138.36,"chartTodayPath":"https://nsearchives.nseindia.com/today/preOpen_TATASTEELEQN.svg"},"detail":{"preOpenMarket":{"preopen":[{"price":138.25,"buyQty":74,"sellQty":0},{"price":138.29,"buyQty":8,"sellQty":0},{"price":138.3,"buyQty":2101,"sellQty":0},{"price":138.33,"buyQty":1332,"sellQty":0},{"price":138.35,"buyQty":1218,"sellQty":0},{"price":138.36,"buyQty":0,"sellQty":6603,"iep":true},{"price":138.4,"buyQty":0,"sellQty":11},{"price":138.5,"buyQty":0,"sellQty":336},{"price":138.59,"buyQty":0,"sellQty":102},{"price":138.6,"buyQty":0,"sellQty":505}],"ato":{"totalBuyQuantity":0,"totalSellQuantity":0},"IEP":138.36,"totalTradedVolume":90484,"finalPrice":138.36,"finalQuantity":90484,"lastUpdateTime":"06-Jan-2025 09:07:05","totalSellQuantity":477087,"totalBuyQuantity":192526,"atoBuyQty":0,"atoSellQty":0,"Change":0,"perChange":0,"prevClose":138.36}}},{"metadata":{"symbol":"EICHERMOT","identifier":"EICHERMOTEQN","purpose":null,"lastPrice":5310.75,"change":0,"pChange":0,"previousClose":5310.75,"finalQuantity":774,"totalTurnover":4110520,"marketCap":729680537874.04,"yearHigh":5385.7,"yearLow":3562.45,"iep":5310.75,"chartTodayPath":"https://nsearchives.nseindia.com/today/preOpen_EICHERMOTEQN.svg"},"detail":{"preOpenMarket":{"preopen":[{"price":5300,"buyQty":9,"sellQty":0},{"price":5300.75,"buyQty":1,"sellQty":0},{"price":5305,"buyQty":5,"sellQty":0},{"price":5305.55,"buyQty":5,"sellQty":0},{"price":5310,"buyQty":71,"sellQty":0},{"price":5310.75,"buyQty":0,"sellQty":242,"iep":true},{"price":5311,"buyQty":0,"sellQty":5},{"price":5313,"buyQty":0,"sellQty":5},{"price":5314.55,"buyQty":0,"sellQty":70},{"price":5315,"buyQty":0,"sellQty":4}],"ato":{"totalBuyQuantity":0,"totalSellQuantity":0},"IEP":5310.75,"totalTradedVolume":774,"finalPrice":5310.75,"finalQuantity":774,"lastUpdateTime":"06-Jan-2025 09:07:07","totalSellQuantity":4077,"totalBuyQuantity":1212,"atoBuyQty":0,"atoSellQty":0,"Change":0,"perChange":0,"prevClose":5310.75}}},{"metadata":{"symbol":"ASIANPAINT","identifier":"ASIANPAINTEQN","purpose":null,"lastPrice":2335.95,"change":0,"pChange":0,"previousClose":2335.95,"finalQuantity":3000,"totalTurnover":7007850,"marketCap":1054149822455.62,"yearHigh":3401.25,"yearLow":2256.5,"iep":2335.95,"chartTodayPath":"https://nsearchives.nseindia.com/today/preOpen_ASIANPAINTEQN.svg"},"detail":{"preOpenMarket":{"preopen":[{"price":2334.25,"buyQty":2,"sellQty":0},{"price":2334.7,"buyQty":1,"sellQty":0},{"price":2335,"buyQty":168,"sellQty":0},{"price":2335.7,"buyQty":6,"sellQty":0},{"price":2335.95,"buyQty":680,"sellQty":0,"iep":true},{"price":2338,"buyQty":0,"sellQty":1},{"price":2340,"buyQty":0,"sellQty":60},{"price":2341,"buyQty":0,"sellQty":40},{"price":2343.3,"buyQty":0,"sellQty":6},{"price":2344,"buyQty":0,"sellQty":102}],"ato":{"totalBuyQuantity":0,"totalSellQuantity":0},"IEP":2335.95,"totalTradedVolume":3000,"finalPrice":2335.95,"finalQuantity":3000,"lastUpdateTime":"06-Jan-2025 09:07:06","totalSellQuantity":20548,"totalBuyQuantity":21931,"atoBuyQty":0,"atoSellQty":0,"Change":0,"perChange":0,"prevClose":2335.95}}},{"metadata":{"symbol":"APOLLOHOSP","identifier":"APOLLOHOSPEQN","purpose":null,"lastPrice":7298.35,"change":0,"pChange":0,"previousClose":7298.35,"finalQuantity":435,"totalTurnover":3174782,"marketCap":740099544199.78,"yearHigh":7545,"yearLow":5640,"iep":7298.35,"chartTodayPath":"https://nsearchives.nseindia.com/today/preOpen_APOLLOHOSPEQN.svg"},"detail":{"preOpenMarket":{"preopen":[{"price":7290,"buyQty":2,"sellQty":0},{"price":7290.5,"buyQty":10,"sellQty":0},{"price":7297.35,"buyQty":1,"sellQty":0},{"price":7298,"buyQty":40,"sellQty":0},{"price":7298.05,"buyQty":3,"sellQty":0},{"price":7298.35,"buyQty":0,"sellQty":44,"iep":true},{"price":7316,"buyQty":0,"sellQty":2},{"price":7321.5,"buyQty":0,"sellQty":10},{"price":7323.9,"buyQty":0,"sellQty":1},{"price":7323.95,"buyQty":0,"sellQty":2}],"ato":{"totalBuyQuantity":0,"totalSellQuantity":0},"IEP":7298.35,"totalTradedVolume":435,"finalPrice":7298.35,"finalQuantity":435,"lastUpdateTime":"06-Jan-2025 09:07:06","totalSellQuantity":2759,"totalBuyQuantity":1247,"atoBuyQty":0,"atoSellQty":0,"Change":0,"perChange":0,"prevClose":7298.35}}},{"metadata":{"symbol":"MARUTI","identifier":"MARUTIEQN","purpose":null,"lastPrice":11929,"change":-5.25,"pChange":-0.04,"previousClose":11934.25,"finalQuantity":604,"totalTurnover":7205116,"marketCap":1563919990543.95,"yearHigh":13680,"yearLow":9737.65,"iep":11929,"chartTodayPath":"https://nsearchives.nseindia.com/today/preOpen_MARUTIEQN.svg"},"detail":{"preOpenMarket":{"preopen":[{"price":11910,"buyQty":5,"sellQty":0},{"price":11911,"buyQty":5,"sellQty":0},{"price":11914.25,"buyQty":1,"sellQty":0},{"price":11920,"buyQty":8,"sellQty":0},{"price":11929,"buyQty":1,"sellQty":0,"iep":true},{"price":11930,"buyQty":0,"sellQty":22},{"price":11932,"buyQty":0,"sellQty":8},{"price":11934.25,"buyQty":0,"sellQty":55},{"price":11935,"buyQty":0,"sellQty":1},{"price":11935.65,"buyQty":0,"sellQty":12}],"ato":{"totalBuyQuantity":0,"totalSellQuantity":0},"IEP":11929,"totalTradedVolume":604,"finalPrice":11929,"finalQuantity":604,"lastUpdateTime":"06-Jan-2025 09:07:05","totalSellQuantity":3684,"totalBuyQuantity":1289,"atoBuyQty":0,"atoSellQty":0,"Change":-5.25,"perChange":-0.04,"prevClose":11934.25}}},{"metadata":{"symbol":"POWERGRID","identifier":"POWERGRIDEQN","purpose":null,"lastPrice":315.8,"change":-0.25,"pChange":-0.08,"previousClose":316.05,"finalQuantity":15817,"totalTurnover":4995008,"marketCap":1428673234042.3,"yearHigh":366.25,"yearLow":226.05,"iep":315.8,"chartTodayPath":"https://nsearchives.nseindia.com/today/preOpen_POWERGRIDEQN.svg"},"detail":{"preOpenMarket":{"preopen":[{"price":315.15,"buyQty":2,"sellQty":0},{"price":315.2,"buyQty":1506,"sellQty":0},{"price":315.3,"buyQty":750,"sellQty":0},{"price":315.6,"buyQty":40,"sellQty":0},{"price":315.8,"buyQty":40,"sellQty":0,"iep":true},{"price":315.85,"buyQty":0,"sellQty":18},{"price":316,"buyQty":0,"sellQty":906},{"price":316.05,"buyQty":0,"sellQty":597},{"price":316.7,"buyQty":0,"sellQty":1},{"price":317,"buyQty":0,"sellQty":35}],"ato":{"totalBuyQuantity":0,"totalSellQuantity":0},"IEP":315.8,"totalTradedVolume":15817,"finalPrice":315.8,"finalQuantity":15817,"lastUpdateTime":"06-Jan-2025 09:07:06","totalSellQuantity":130259,"totalBuyQuantity":70060,"atoBuyQty":0,"atoSellQty":0,"Change":-0.25,"perChange":-0.08,"prevClose":316.05}}},{"metadata":{"symbol":"BHARTIARTL","identifier":"BHARTIARTLEQN","purpose":null,"lastPrice":1596.15,"change":-2.7,"pChange":-0.17,"previousClose":1598.85,"finalQuantity":4836,"totalTurnover":7718981,"marketCap":4269610159499.18,"yearHigh":1779,"yearLow":1021.35,"iep":1596.15,"chartTodayPath":"https://nsearchives.nseindia.com/today/preOpen_BHARTIARTLEQN.svg"},"detail":{"preOpenMarket":{"preopen":[{"price":1595.5,"buyQty":1000,"sellQty":0},{"price":1595.55,"buyQty":40,"sellQty":0},{"price":1596,"buyQty":25,"sellQty":0},{"price":1596.05,"buyQty":4,"sellQty":0},{"price":1596.15,"buyQty":23,"sellQty":0,"iep":true},{"price":1598.75,"buyQty":0,"sellQty":93},{"price":1598.85,"buyQty":0,"sellQty":731},{"price":1598.95,"buyQty":0,"sellQty":1},{"price":1599,"buyQty":0,"sellQty":1},{"price":1600,"buyQty":0,"sellQty":32}],"ato":{"totalBuyQuantity":0,"totalSellQuantity":0},"IEP":1596.15,"totalTradedVolume":4836,"finalPrice":1596.15,"finalQuantity":4836,"lastUpdateTime":"06-Jan-2025 09:07:06","totalSellQuantity":23276,"totalBuyQuantity":391533,"atoBuyQty":0,"atoSellQty":0,"Change":-2.7,"perChange":-0.17,"prevClose":1598.85}}},{"metadata":{"symbol":"ADANIENT","identifier":"ADANIENTEQN","purpose":null,"lastPrice":2557.65,"change":-6.95,"pChange":-0.27,"previousClose":2564.6,"finalQuantity":1722,"totalTurnover":4404273,"marketCap":637034799719.04,"yearHigh":3743.9,"yearLow":2025,"iep":2557.65,"chartTodayPath":"https://nsearchives.nseindia.com/today/preOpen_ADANIENTEQN.svg"},"detail":{"preOpenMarket":{"preopen":[{"price":2556.9,"buyQty":13,"sellQty":0},{"price":2557,"buyQty":8,"sellQty":0},{"price":2557.05,"buyQty":126,"sellQty":0},{"price":2557.6,"buyQty":50,"sellQty":0},{"price":2557.65,"buyQty":218,"sellQty":0,"iep":true},{"price":2559,"buyQty":0,"sellQty":500},{"price":2561.55,"buyQty":0,"sellQty":1},{"price":2562,"buyQty":0,"sellQty":1},{"price":2563,"buyQty":0,"sellQty":1},{"price":2564,"buyQty":0,"sellQty":3}],"ato":{"totalBuyQuantity":0,"totalSellQuantity":0},"IEP":2557.65,"totalTradedVolume":1722,"finalPrice":2557.65,"finalQuantity":1722,"lastUpdateTime":"06-Jan-2025 09:07:10","totalSellQuantity":14305,"totalBuyQuantity":4322,"atoBuyQty":0,"atoSellQty":0,"Change":-6.95,"perChange":-0.27,"prevClose":2564.6}}},{"metadata":{"symbol":"TATACONSUM","identifier":"TATACONSUMEQN","purpose":null,"lastPrice":935,"change":-4.45,"pChange":-0.47,"previousClose":939.45,"finalQuantity":2310,"totalTurnover":2159850,"marketCap":608040756353.97,"yearHigh":1256.44,"yearLow":882.9,"iep":935,"chartTodayPath":"https://nsearchives.nseindia.com/today/preOpen_TATACONSUMEQN.svg"},"detail":{"preOpenMarket":{"preopen":[{"price":932.8,"buyQty":5,"sellQty":0},{"price":933,"buyQty":1,"sellQty":0},{"price":933.8,"buyQty":10,"sellQty":0},{"price":934,"buyQty":50,"sellQty":0},{"price":934.4,"buyQty":25,"sellQty":0},{"price":935,"buyQty":0,"sellQty":1081,"iep":true},{"price":935.5,"buyQty":0,"sellQty":1},{"price":936,"buyQty":0,"sellQty":26},{"price":938,"buyQty":0,"sellQty":66},{"price":938.05,"buyQty":0,"sellQty":10}],"ato":{"totalBuyQuantity":0,"totalSellQuantity":0},"IEP":935,"totalTradedVolume":2310,"finalPrice":935,"finalQuantity":2310,"lastUpdateTime":"06-Jan-2025 09:07:08","totalSellQuantity":30126,"totalBuyQuantity":6717,"atoBuyQty":0,"atoSellQty":0,"Change":-4.45,"perChange":-0.47,"prevClose":939.45}}},{"metadata":{"symbol":"HDFCBANK","identifier":"HDFCBANKEQN","purpose":null,"lastPrice":1740.1,"change":-9.1,"pChange":-0.52,"previousClose":1749.2,"finalQuantity":267586,"totalTurnover":465626398,"marketCap":13279216840815.78,"yearHigh":1880,"yearLow":1363.55,"iep":1740.1,"chartTodayPath":"https://nsearchives.nseindia.com/today/preOpen_HDFCBANKEQN.svg"},"detail":{"preOpenMarket":{"preopen":[{"price":1739,"buyQty":62,"sellQty":0},{"price":1739.2,"buyQty":18,"sellQty":0},{"price":1740,"buyQty":40328,"sellQty":0},{"price":1740.05,"buyQty":146,"sellQty":0},{"price":1740.1,"buyQty":33460,"sellQty":0,"iep":true},{"price":1740.5,"buyQty":0,"sellQty":52},{"price":1740.6,"buyQty":0,"sellQty":50},{"price":1742,"buyQty":0,"sellQty":103},{"price":1744,"buyQty":0,"sellQty":51},{"price":1745,"buyQty":0,"sellQty":1631}],"ato":{"totalBuyQuantity":0,"totalSellQuantity":0},"IEP":1740.1,"totalTradedVolume":267586,"finalPrice":1740.1,"finalQuantity":267586,"lastUpdateTime":"06-Jan-2025 09:07:05","totalSellQuantity":211846,"totalBuyQuantity":202446,"atoBuyQty":0,"atoSellQty":0,"Change":-9.1,"perChange":-0.52,"prevClose":1749.2}}},{"metadata":{"symbol":"SHRIRAMFIN","identifier":"SHRIRAMFINEQN","purpose":null,"lastPrice":3031,"change":-17.35,"pChange":-0.57,"previousClose":3048.35,"finalQuantity":3621,"totalTurnover":10975251,"marketCap":852844408543.04,"yearHigh":3652.25,"yearLow":2029,"iep":3031,"chartTodayPath":"https://nsearchives.nseindia.com/today/preOpen_SHRIRAMFINEQN.svg"},"detail":{"preOpenMarket":{"preopen":[{"price":3024.15,"buyQty":2,"sellQty":0},{"price":3025,"buyQty":101,"sellQty":0},{"price":3025.05,"buyQty":10,"sellQty":0},{"price":3028,"buyQty":30,"sellQty":0},{"price":3030,"buyQty":68,"sellQty":0},{"price":3030.7,"buyQty":0,"sellQty":24},{"price":3031,"buyQty":0,"sellQty":83,"iep":true},{"price":3034.5,"buyQty":0,"sellQty":25},{"price":3039,"buyQty":0,"sellQty":1},{"price":3040.35,"buyQty":0,"sellQty":1}],"ato":{"totalBuyQuantity":0,"totalSellQuantity":0},"IEP":3031,"totalTradedVolume":3621,"finalPrice":3031,"finalQuantity":3621,"lastUpdateTime":"06-Jan-2025 09:07:06","totalSellQuantity":11708,"totalBuyQuantity":1934,"atoBuyQty":0,"atoSellQty":0,"Change":-17.35,"perChange":-0.57,"prevClose":3048.35}}},{"metadata":{"symbol":"CIPLA","identifier":"CIPLAEQN","purpose":null,"lastPrice":1500,"change":-11.25,"pChange":-0.74,"previousClose":1511.25,"finalQuantity":6889,"totalTurnover":10333500,"marketCap":827579565384.51,"yearHigh":1702.05,"yearLow":1266.2,"iep":1500,"chartTodayPath":"https://nsearchives.nseindia.com/today/preOpen_CIPLAEQN.svg"},"detail":{"preOpenMarket":{"preopen":[{"price":1496.05,"buyQty":5,"sellQty":0},{"price":1498,"buyQty":25,"sellQty":0},{"price":1499,"buyQty":18,"sellQty":0},{"price":1499.7,"buyQty":14,"sellQty":0},{"price":1499.95,"buyQty":1,"sellQty":0},{"price":1500,"buyQty":0,"sellQty":1505,"iep":true},{"price":1503.5,"buyQty":0,"sellQty":4},{"price":1503.55,"buyQty":0,"sellQty":4},{"price":1511.2,"buyQty":0,"sellQty":2},{"price":1511.25,"buyQty":0,"sellQty":330}],"ato":{"totalBuyQuantity":0,"totalSellQuantity":0},"IEP":1500,"totalTradedVolume":6889,"finalPrice":1500,"finalQuantity":6889,"lastUpdateTime":"06-Jan-2025 09:07:05","totalSellQuantity":19094,"totalBuyQuantity":3670,"atoBuyQty":0,"atoSellQty":0,"Change":-11.25,"perChange":-0.74,"prevClose":1511.25}}},{"metadata":{"symbol":"KOTAKBANK","identifier":"KOTAKBANKEQN","purpose":null,"lastPrice":1821,"change":-17.65,"pChange":-0.96,"previousClose":1838.65,"finalQuantity":22214,"totalTurnover":40451694,"marketCap":2692073689570.56,"yearHigh":1942,"yearLow":1543.85,"iep":1821,"chartTodayPath":"https://nsearchives.nseindia.com/today/preOpen_KOTAKBANKEQN.svg"},"detail":{"preOpenMarket":{"preopen":[{"price":1819.8,"buyQty":50,"sellQty":0},{"price":1820,"buyQty":2055,"sellQty":0},{"price":1820.2,"buyQty":1,"sellQty":0},{"price":1820.65,"buyQty":1,"sellQty":0},{"price":1821,"buyQty":6485,"sellQty":0,"iep":true},{"price":1824.2,"buyQty":0,"sellQty":10},{"price":1825,"buyQty":0,"sellQty":232},{"price":1825.8,"buyQty":0,"sellQty":50},{"price":1827,"buyQty":0,"sellQty":20},{"price":1827.4,"buyQty":0,"sellQty":3}],"ato":{"totalBuyQuantity":0,"totalSellQuantity":0},"IEP":1821,"totalTradedVolume":22214,"finalPrice":1821,"finalQuantity":22214,"lastUpdateTime":"06-Jan-2025 09:10:02","totalSellQuantity":35374,"totalBuyQuantity":20165,"atoBuyQty":0,"atoSellQty":0,"Change":-17.65,"perChange":-0.96,"prevClose":1838.65}}}],"advances":32,"timestamp":"06-Jan-2025 09:07:05","totalTradedValue":1077676534,"totalmarketcap":103093038771194.89,"totalTradedVolume":913299,"niftyPreopenStatus":{"pChange":"0.17","lastPrice":"24045.8","change":"41.04999999999927","status":"CLOSED"}}